README.rst
setup.py
hollowpoint/__init__.py
hollowpoint.egg-info/PKG-INFO
hollowpoint.egg-info/SOURCES.txt
hollowpoint.egg-info/dependency_links.txt
hollowpoint.egg-info/top_level.txt